common_executor/__init__.py
common_executor/exec/__init__.py
common_executor/utypes/__init__.py
common_executor-0.1.0.dist-info/METADATA
common_executor-0.1.0.dist-info/WHEEL
common_executor-0.1.0.dist-info/RECORD
