Metadata-Version: 2.3
Name: common-executor
Version: 0.1.0
Summary: Execute Python code in an automatically generated TUI App.
Project-URL: documentation, https://rhuygen.github.io/common-executor/
Project-URL: repository, https://github.com/rhuygen/common-executor
Author-email: Rik Huygen <rik.huygen@kuleuven.be>
License: MIT
Keywords: GUI,TUI,common,execute,lab,task
Classifier: Development Status :: 2 - Pre-Alpha
Classifier: Environment :: Console
Classifier: License :: OSI Approved :: MIT License
Classifier: Programming Language :: Python :: 3.8
Classifier: Programming Language :: Python :: 3.9
Classifier: Programming Language :: Python :: 3.10
Classifier: Programming Language :: Python :: 3.11
Classifier: Programming Language :: Python :: 3.12
Classifier: Topic :: Utilities
Requires-Python: >=3.8
Provides-Extra: test
Requires-Dist: pytest; extra == 'test'
